turbines/__init__.py
turbines/builder.py
turbines/config_loader.py
turbines/reader.py
turbines/scaffold/config.yaml
turbines/scaffold/pages/index.html
turbines/scaffold/pages/test.md
turbines/scaffold/static/script.js
turbines/scaffold/static/style.css
turbines/scaffold/templates/base.html
turbines/server.py
turbines-0.1.2.dist-info/WHEEL
turbines-0.1.2.dist-info/entry_points.txt
turbines-0.1.2.dist-info/METADATA
turbines-0.1.2.dist-info/RECORD
