Metadata-Version: 2.3
Name: turbines
Version: 0.1.2
Summary: A simple static site generator with live reload
Author: nfast
Author-email: nfast <turbines@nilsfast.com>
Requires-Dist: jinja2>=3.1.6
Requires-Dist: jinja2-simple-tags>=0.6.1
Requires-Dist: markdown>=3.10
Requires-Dist: pydantic>=2.12.5
Requires-Dist: pytest>=9.0.2
Requires-Dist: pyyaml>=6.0.3
Requires-Dist: tornado>=6.5.3
Requires-Dist: typer>=0.20.0
Requires-Dist: watchdog>=6.0.0
Requires-Dist: websockets>=15.0.1
Requires-Python: >=3.12
